{
    "title": "UML Use Case",
    "items": [
        {
            "type": "text",
            "data": [
                {
                    "text": "1. Идентификатор прецендента",
                    "class": "md-title"
                }
            ]
        },
        {
            "type": "text",
            "data": [
                {
                    "text": "Выпускная квалификационная работа "
                }
            ]
        },
        {
            "type": "text",
            "data": [
                {
                    "text": "2. Название прецендента"
                }
            ]
        },
        {
            "type": "image",
            "data": "img/use-case-diagram.png"
        },
        {
            "type": "text",
            "data": [
                {
                    "text": "Разметка личной страницы, разработка UML Use Case"
                }
            ]
        },
        {"type": "text",
            "data": [
                {
                    "text": "3. Контекст",
                    "class": "md-title"
                }
            ]
        }
    ]
}
